yimage/__init__.py
yimage/__version__.cp36-win_amd64.pyd
yimage/io.cp36-win_amd64.pyd
yimage/_internal/__init__.py
yimage/_internal/_io.cp36-win_amd64.pyd
yimage-1.1.0.dist-info/LICENSE
yimage-1.1.0.dist-info/METADATA
yimage-1.1.0.dist-info/WHEEL
yimage-1.1.0.dist-info/top_level.txt
yimage-1.1.0.dist-info/RECORD
