Metadata-Version: 2.1
Name: yimage
Version: 1.1.0
Summary: A friendly remote sensing data library
Home-page: UNKNOWN
Author: Xuan Yang
Author-email: yangxuan.ac@gmail.com
License: MIT
Requires-Dist: numpy (>=1.16.0)
Requires-Dist: opencv-python (>=4.0.0)
Requires-Dist: Cython (>=0.29.0)
